Workbook
Name BalCheck: Model!$G$115
Name Circularity: Cover!$C$14
Name Million: Assumptions!$F$9
Name S_List: Scenario!$D$12:$D$14
Name S_Scenario: Scenario!$F$9

Sheet Cover
B4: =Historical!B2 -> Xcel Stores & Properties
B6: ="Financial Forecast from "&Historical!I7+1&" to "&Historical!I7+5 -> Financial Forecast from 2023 to 2027
B8: Version | C8: V1.01
B10: Modeller: | C10: Animashaun Jafar
B12: Circularity in the Model: | C12: Net Interest Expense
B14: Circularity Switch>>>>> | C14: 2
B17: =IF(Circularity=1,"Circularity is now turned on in the model, kindly follow the steps below to enable iterative calculation:","")
B19: =IF(Circularity=1,"Click on File>>Options>>Formulas>>Calculation Options>>Check Enable Iterative Calculation>>OK","")
B20: =IF(Circularity=1,"Alternatively, use the Excel Shortcut ALT + F + T to quickly navigate to Excel Options, then follow other steps as stated above","")
B22: © This Model is a copyright material of dbrownconsulting. It is solely for educational purpose and should not be used otherwise without prior written permission.

Sheet Historical
B2: Xcel Stores & Properties
B3: Income Statement
B5: Millions for the Year Ended December 31
G7: 2020 | H7: =G7+1 -> 2021 | I7: =H7+1 -> 2022
B9: Revenue Growth | H9: =H13/G13-1 -> 0.1050833 | I9: =I13/H13-1 -> 0.078082721
B10: COGS (% of revenue) | G10: =G15/G$13 -> 0.31866724 | H10: =H15/H$13 -> 0.35485118 | I10: =I15/I$13 -> 0.36894944
B11: SG&A (% of revenue) | G11: =G16/G$13 -> 0.061939342 | H11: =H16/H$13 -> 0.065326633 | I11: =I16/I$13 -> 0.070993188
C13: Revenue | G13: 234.1 | H13: 258.7 | I13: 278.9
C15: Operating Costs | G15: 74.6 | H15: 91.8 | I15: 102.9
C16: SG&A | G16: 14.5 | H16: 16.9 | I16: 19.8
C17: Total Costs | G17: =SUM(G15:G16) -> 89.1 | H17: =SUM(H15:H16) -> 108.7 | I17: =SUM(I15:I16) -> 122.7
C19: Cost Adjustments - Gain / (Loss) | G19: 0 | H19: 0.8 | I19: 2.3
C20: EBITDA | G20: =G13-G17+G19 -> 145 | H20: =H13-H17+H19 -> 150.8 | I20: =I13-I17+I19 -> 158.5
C22: Depreciation | G22: 41.7 | H22: 46.2 | I22: 54.6
C23: EBIT | G23: =G20-G22 -> 103.3 | H23: =H20-H22 -> 104.6 | I23: =I20-I22 -> 103.9
C25: Foreign Exchange - Gain / (Loss) | G25: 0 | H25: -2.6 | I25: 0
C26: Net Interest Expense | G26: 33.5 | H26: 34.2 | I26: 36.6
C27: EBT | G27: =G23+G25-G26 -> 69.8 | H27: =H23+H25-H26 -> 67.8 | I27: =I23+I25-I26 -> 67.3
C29: Current Taxes | G29: 11.3 | H29: 10.5 | I29: 15.8
C30: Deferred Income Taxes | G30: 10.4 | H30: 11.8 | I30: 8.4
C31: Total Income Taxes | G31: =SUM(G29:G30) -> 21.7 | H31: =SUM(H29:H30) -> 22.3 | I31: =SUM(I29:I30) -> 24.2
C33: Net Income | G33: =G27-G31 -> 48.1 | H33: =H27-H31 -> 45.5 | I33: =I27-I31 -> 43.1
C35: Preferred Dividend | G35: 0 | H35: 0 | I35: 0
C36: Net Income to Common | G36: =G33-G35 -> 48.1 | H36: =H33-H35 -> 45.5 | I36: =I33-I35 -> 43.1
B41: =$B$2 -> Xcel Stores & Properties
B42: Cash Flow Statement
B44: =$B$5 -> Millions for the Year Ended December 31
G46: =G$7 -> 2020 | H46: =H$7 -> 2021 | I46: =I$7 -> 2022
B48: Operating Activities
C49: Net Income | G49: 48.1 | H49: 45.5 | I49: 43.1
C50: Depreciation | G50: 41.7 | H50: 46.2 | I50: 54.6
C51: Deferred Income Taxes | G51: 10.4 | H51: 11.8 | I51: 8.4
C52: Changes in Working Capital | G52: 2.4 | H52: 6.7 | I52: -3.3
C53: Other | G53: 0.4 | H53: -0.4 | I53: -0.3
C54: Operating Cash Flow | G54: =SUM(G49:G53) -> 103 | H54: =SUM(H49:H53) -> 109.8 | I54: =SUM(I49:I53) -> 102.5
B57: Investing Activities
C58: CAPEX | G58: -121.1 | H58: -159.7 | I58: -151.2
C59: Asset Dispositions | G59: 23.4 | H59: 13.8 | I59: 5.8
C60: Other | G60: 2.5 | H60: 2.6 | I60: 0.8
C61: Investing Cash Flow | G61: =SUM(G58:G60) -> -95.2 | H61: =SUM(H58:H60) -> -143.3 | I61: =SUM(I58:I60) -> -144.6
B64: Financing Activities
C65: Revolver Issuance / (Repayment) | G65: 0 | H65: 0 | I65: 0
C66: Variable Rate Long Term Debt Issuance / (Repayment) | G66: -26 | H66: 20 | I66: 25
C67: Fixed Rate Long Term Debt Issuance / (Repayment) | G67: 5 | H67: 25 | I67: 25
C68: Preferred Share Issuance / (Buy-Back) | G68: 0 | H68: 0 | I68: 0
C69: Common Share Issuance / (Buy-Back) | G69: -5 | H69: -4 | I69: -6
C70: Preferred Share Dividends | G70: 0 | H70: 0 | I70: 0
C71: Common Share Dividends | G71: -7.2 | H71: -9.6 | I71: -9.1
C72: Other | G72: 0.8 | H72: 0.6 | I72: -0.5
C73: Financing Cash Flow | G73: =SUM(G65:G72) -> -32.4 | H73: =SUM(H65:H72) -> 32 | I73: =SUM(I65:I72) -> 34.4
C75: Change in Cash Position | G75: =G73+G61+G54 -> -24.6 | H75: =H73+H61+H54 -> -1.5 | I75: =I73+I61+I54 -> -7.7
C76: Beginning Cash | G76: 232.8 | H76: =G77 -> 208.2 | I76: =H77 -> 206.7
C77: Ending Cash | G77: =G76+G75 -> 208.2 | H77: =H76+H75 -> 206.7 | I77: =I76+I75 -> 199
B81: =$B$2 -> Xcel Stores & Properties
B82: Balance Sheet
B84: =$B$5 -> Millions for the Year Ended December 31
G85: =G$7 -> 2020 | H85: =H$7 -> 2021 | I85: =I$7 -> 2022
B86: ASSETS
C87: Cash and Equivalents | G87: 208.2 | H87: 206.7 | I87: 199
C88: Accounts Receivable | G88: 16 | H88: 15.1 | I88: 20.2
C89: Inventory | G89: 2.8 | H89: 3.6 | I89: 4.2
C90: Other Current Assets | G90: 0.3 | H90: 0.2 | I90: 0.2
C91: Total Current Assets | G91: =SUM(G87:G90) -> 227.3 | H91: =SUM(H87:H90) -> 225.6 | I91: =SUM(I87:I90) -> 223.6
C93: Net PP&E | G93: 2332.1 | H93: 2445.6 | I93: 2542.2
C94: Goodwill | G94: 46.6 | H94: 34.7 | I94: 31
C95: Intangibles | G95: 15.5 | H95: 14.7 | I95: 13.1
C96: Other Long term Assets | G96: 4.2 | H96: 3.5 | I96: 2.1
C97: Total Long Term Assets | G97: =SUM(G93:G96) -> 2398.4 | H97: =SUM(H93:H96) -> 2498.5 | I97: =SUM(I93:I96) -> 2588.4
C99: Total Assets | G99: =G91+G97 -> 2625.7 | H99: =H91+H97 -> 2724.1 | I99: =I91+I97 -> 2812
B102: LIABILITIES AND EQUITY
C103: Bank Debt - Revolver | G103: 0 | H103: 0 | I103: 0
C104: Accounts Payable | G104: 14.9 | H104: 21.5 | I104: 23.9
C105: Other Current Liabilities | G105: 4.6 | H105: 5.1 | I105: 4.9
C106: Total Current Liabilities | G106: =SUM(G103:G105) -> 19.5 | H106: =SUM(H103:H105) -> 26.6 | I106: =SUM(I103:I105) -> 28.8
C108: Variable Rate Long Term Debt | G108: 577.7 | H108: 597.7 | I108: 622.7
C109: Fixed Rate Long Term Debt | G109: 174.6 | H109: 199.6 | I109: 224.6
C110: Deferred Income Taxes | G110: 10.4 | H110: 22.2 | I110: 30.6
C111: Other Longterm Liabilities | G111: 2.4 | H111: 3.6 | I111: 3.2
C112: Total Long Term Liabilities | G112: =SUM(G108:G111) -> 765.1 | H112: =SUM(H108:H111) -> 823.1 | I112: =SUM(I108:I111) -> 881.1
C114: Total Liabilities | G114: =G106+G112 -> 784.6 | H114: =H106+H112 -> 849.7 | I114: =I106+I112 -> 909.9
C116: Preferred Shares | G116: 0 | H116: 0 | I116: 0
C117: Common Shares | G117: 1653.2 | H117: 1649.2 | I117: 1643.2
C118: Retained Earnings | G118: 175.1 | H118: 211 | I118: 245
C119: Other Shareholder equity | G119: 12.8 | H119: 14.2 | I119: 13.9
C120: Shareholder's Equity | G120: =SUM(G116:G119) -> 1841.1 | H120: =SUM(H116:H119) -> 1874.4 | I120: =SUM(I116:I119) -> 1902.1
B122: Total Liabilities and Equity | G122: =G120+G114 -> 2625.7 | H122: =H120+H114 -> 2724.1 | I122: =I120+I114 -> 2812
G126: =G122-G99 -> 0 | H126: =H122-H99 -> 0 | I126: =I122-I99 -> 0

Sheet Summary
B2: =Cover!B4 -> Xcel Stores & Properties
C3: Executive Summary | I3: =IF(BalCheck=0,"Bal check: OK","ERROR") -> Bal check: OK | K3: {="Scenario: "&INDEX(S_List,S_Scenario)} -> Scenario: Base Case
I4: Actual | J4: Actual | K4: Actual | L4: Forecast | M4: Forecast | N4: Forecast | O4: Forecast | P4: Forecast
E5: units | F5: Inputs/drivers | I5: =Historical!G7 -> 2020 | J5: =I5+1 -> 2021 | K5: =J5+1 -> 2022 | L5: =K5+1 -> 2023 | M5: =L5+1 -> 2024 | N5: =M5+1 -> 2025 | O5: =N5+1 -> 2026 | P5: =O5+1 -> 2027 | R5: 2
B7: Analysis Based on: Base Case Scenario
C9: Revenue
D10: Net Revenue | E10: $MM | I10: 234.1 | J10: 258.7 | K10: 278.9 | L10: 304.2883 | M10: 330.94888 | N10: 358.93525 | O10: 388.30293 | P10: 419.10964
D11: Growth Rate | E11: % | I11: 0 | J11: 0.1050833 | K11: 0.078082721 | L11: 0.091030111 | M11: 0.087616205 | N11: 0.084564 | O11: 0.081818906 | P11: 0.079336791
C13: EBITDA
D14: EBITDA | E14: $MM | I14: 145 | J14: 150.8 | K14: 158.5 | L14: 124.14137 | M14: 138.42947 | N14: 153.46312 | O14: 169.27421 | P14: 185.89585
D15: EBITDA Margin | E15: % | I15: 0.61939342 | J15: 0.58291457 | K15: 0.56830405 | L15: 0.40797287 | M15: 0.41828051 | N15: 0.427551 | O15: 0.43593338 | P15: 0.44354944
D16: EBITDA growth rate | E16: % | I16: 0 | J16: 0.04 | K16: 0.051061008 | L16: -0.21677369 | M16: 0.11509537 | N16: 0.10860155 | O16: 0.10302858 | P16: 0.098193554
C18: Net Income
D19: Net Income | E19: $MM | I19: 48.1 | J19: 45.5 | K19: 43.1 | L19: 13.836906 | M19: 19.511661 | N19: 21.802243 | O19: 23.241398 | P19: 26.280825
D20: Net Income Margin | E20: % | I20: 0.20546775 | J20: 0.1758794 | K20: 0.15453568 | L20: 0.045473014 | M20: 0.058956722 | N20: 0.060741438 | O20: 0.059853779 | P20: 0.062706325
D21: Net Income Growth rate | E21: % | I21: 0 | J21: -0.054054054 | K21: -0.052747253 | L21: -0.67895809 | M21: 0.41011734 | N21: 0.11739551 | O21: 0.066009497 | P21: 0.13077646
C23: Dupont Analysis
D24: Return on Equity | E24: % | I24: 0.026125686 | J24: 0.024274434 | K24: 0.022659166 | L24: 0.0072709825 | M24: 0.0079331956 | N24: 0.009039658 | O24: 0.0096955982 | P24: 0.01112844
D25: Net Profit Margin | E25: % | I25: 0.20546775 | J25: 0.1758794 | K25: 0.15453568 | L25: 0.045473014 | M25: 0.058956722 | N25: 0.060741438 | O25: 0.059853779 | P25: 0.062706325
D26: Asset Turnover | E26: Multiple | I26: 0.089157177 | J26: 0.094967145 | K26: 0.099182077 | L26: 0.11281301 | M26: 0.11950493 | N26: 0.12637758 | O26: 0.13388275 | P26: 0.14202352
D27: Financial Leverage | E27: Multiple | I27: 1.4261583 | J27: 1.4533184 | K27: 1.478366 | L27: 1.4173599 | M27: 1.4163317 | N27: 1.442193 | O27: 1.4614503 | P27: 1.4739081
B30: Analysis Based on: Best Case Scenario
C32: Revenue
D33: Net Revenue | E33: $MM | I33: 234.1 | J33: 258.7 | K33: 278.9 | L33: 309.70698 | M33: 339.4467 | N33: 370.6941 | O33: 403.51293 | P33: 437.96938
D34: Growth Rate | E34: % | I34: 0 | J34: 0.1050833 | K34: 0.078082721 | L34: 0.11045887 | M34: 0.096025338 | N34: 0.092053935 | O34: 0.088533449 | P34: 0.085391204
C36: EBITDA
D37: EBITDA | E37: $MM | I37: 145 | J37: 150.8 | K37: 158.5 | L37: 129.94976 | M37: 148.12199 | N37: 167.41111 | O37: 187.86985 | P37: 209.55313
D38: EBITDA Margin | E38: % | I38: 0.61939342 | J38: 0.58291457 | K38: 0.56830405 | L38: 0.41958937 | M38: 0.43636303 | N38: 0.45161525 | O38: 0.46558571 | P38: 0.47846526
D39: EBITDA growth rate | E39: % | I39: 0 | J39: 0.04 | K39: 0.051061008 | L39: -0.18012771 | M39: 0.13984044 | N39: 0.13022456 | O39: 0.1222066 | P39: 0.1154165
C41: Net Income
D42: Net Income | E42: $MM | I42: 48.1 | J42: 45.5 | K42: 43.1 | L42: 17.757568 | M42: 26.152332 | N42: 31.497753 | O42: 36.343915 | P42: 43.167674
D43: Net Income Margin | E43: % | I43: 0.20546775 | J43: 0.1758794 | K43: 0.15453568 | L43: 0.057336672 | M43: 0.077044002 | N43: 0.084969662 | O43: 0.090068774 | P43: 0.098563223
D44: Net Income Growth rate | E44: % | I44: 0 | J44: -0.054054054 | K44: -0.052747253 | L44: -0.58799147 | M44: 0.47274293 | N44: 0.20439556 | O44: 0.1538574 | P44: 0.18775521
C46: Dupont Analysis
D47: Return on Equity | E47: % | I47: 0.026125686 | J47: 0.024274434 | K47: 0.022659166 | L47: 0.0093160391 | M47: 0.011281324 | N47: 0.013850316 | O47: 0.016084268 | P47: 0.01918248
D48: Net Profit Margin | E48: % | I48: 0.20546775 | J48: 0.1758794 | K48: 0.15453568 | L48: 0.057336672 | M48: 0.077044002 | N48: 0.084969662 | O48: 0.090068774 | P48: 0.098563223
D49: Asset Turnover | E49: Multiple | I49: 0.089157177 | J49: 0.094967145 | K49: 0.099182077 | L49: 0.11480733 | M49: 0.1225503 | N49: 0.13048509 | O49: 0.13908376 | P49: 0.14835936
D50: Financial Leverage | E50: Multiple | I50: 1.4261583 | J50: 1.4533184 | K50: 1.478366 | L50: 1.4152371 | M50: 1.4105803 | N50: 1.4309263 | O50: 1.4427456 | P50: 1.4457919
B52: Analysis Based on: Worst Case Scenario
C54: Revenue
D55: Net Revenue | E55: $MM | I55: 234.1 | J55: 258.7 | K55: 278.9 | L55: 298.9247 | M55: 322.56855 | N55: 347.36407 | O55: 373.35917 | P55: 400.60361
D56: Growth Rate | E56: % | I56: 0 | J56: 0.1050833 | K56: 0.078082721 | L56: 0.07179886 | M56: 0.079096321 | N56: 0.076869003 | O56: 0.074835332 | P56: 0.072971111
C58: EBITDA
D59: EBITDA | E59: $MM | I59: 145 | J59: 150.8 | K59: 158.5 | L59: 118.40996 | M59: 128.91318 | N59: 139.80566 | O59: 151.09532 | P59: 162.78996
D60: EBITDA Margin | E60: % | I60: 0.61939342 | J60: 0.58291457 | K60: 0.56830405 | L60: 0.39611969 | M60: 0.39964585 | N60: 0.40247587 | O60: 0.40469158 | P60: 0.4063617
D61: EBITDA growth rate | E61: % | I61: 0 | J61: 0.04 | K61: 0.051061008 | L61: -0.252934 | M61: 0.08870217 | N61: 0.084494638 | O61: 0.080752529 | P61: 0.077399133
C63: Net Income
D64: Net Income | E64: $MM | I64: 48.1 | J64: 45.5 | K64: 43.1 | L64: 9.9682054 | M64: 12.991148 | N64: 12.307083 | O64: 10.429706 | P64: 9.7835218
D65: Net Income Margin | E65: % | I65: 0.20546775 | J65: 0.1758794 | K65: 0.15453568 | L65: 0.033346877 | M65: 0.040274069 | N65: 0.035429924 | O65: 0.027934779 | P65: 0.024421951
D66: Net Income Growth rate | E66: % | I66: 0 | J66: -0.054054054 | K66: -0.052747253 | L66: -0.76871913 | M66: 0.30325845 | N66: -0.052656271 | O66: -0.15254439 | P66: -0.061956139
C68: Dupont Analysis
D69: Return on Equity | E69: % | I69: 0.026125686 | J69: 0.024274434 | K69: 0.022659166 | L69: 0.0052464933 | M69: 0.0046177649 | N69: 0.004252104 | O69: 0.0032826061 | P69: 0.0029458332
D70: Net Profit Margin | E70: % | I70: 0.20546775 | J70: 0.1758794 | K70: 0.15453568 | L70: 0.033346877 | M70: 0.040274069 | N70: 0.035429924 | O70: 0.027934779 | P70: 0.024421951
D71: Asset Turnover | E71: Multiple | I71: 0.089157177 | J71: 0.094967145 | K71: 0.099182077 | L71: 0.1108385 | M71: 0.1165006 | N71: 0.12233376 | O71: 0.12876985 | P71: 0.13580223
D72: Financial Leverage | E72: Multiple | I72: 1.4261583 | J72: 1.4533184 | K72: 1.478366 | L72: 1.4194604 | M72: 1.4220358 | N72: 1.4534294 | O72: 1.4802678 | P72: 1.5025321
B75: Summary Generator
B76: {="Analysis Based on: "&INDEX(S_List,S_Scenario)&" Scenario"} -> Analysis Based on: Base Case Scenario
C78: Revenue
D79: Net Revenue | E79: $MM | I79: =Model!I11 -> 234.1 | J79: =Model!J11 -> 258.7 | K79: =Model!K11 -> 278.9 | L79: =Model!L11 -> 307.77985 | M79: =Model!M11 -> 338.14147 | N79: =Model!N11 -> 370.0478 | O79: =Model!O11 -> 403.56417 | P79: =Model!P11 -> 423.36689 | R79: =IF($R$5=1,_xlfn.FORMULATEXT(P79),"")
D80: Growth Rate | E80: % | I80: =IFERROR(I79/H79-1,0) -> 0 | J80: =IFERROR(J79/I79-1,0) -> 0.1050833 | K80: =IFERROR(K79/J79-1,0) -> 0.078082721 | L80: =IFERROR(L79/K79-1,0) -> 0.10354911 | M80: =IFERROR(M79/L79-1,0) -> 0.098647222 | N80: =IFERROR(N79/M79-1,0) -> 0.09435791 | O80: =IFERROR(O79/N79-1,0) -> 0.090573096 | P80: =IFERROR(P79/O79-1,0) -> 0.049069573 | R80: =IF($R$5=1,_xlfn.FORMULATEXT(P80),"")
C82: EBITDA
D83: EBITDA | E83: $MM | I83: =Model!I18 -> 145 | J83: =Model!J18 -> 150.8 | K83: =Model!K18 -> 158.5 | L83: =Model!L18 -> 171.90114 | M83: =Model!M18 -> 193.14795 | N83: =Model!N18 -> 215.51485 | O83: =Model!O18 -> 239.04993 | P83: =Model!P18 -> 252.08201 | R83: =IF($R$5=1,_xlfn.FORMULATEXT(P83),"")
D84: EBITDA Margin | E84: % | I84: =I83/I$79 -> 0.61939342 | J84: =J83/J$79 -> 0.58291457 | K84: =K83/K$79 -> 0.56830405 | L84: =L83/L$79 -> 0.5585198 | M84: =M83/M$79 -> 0.57120454 | N84: =N83/N$79 -> 0.58239733 | O84: =O83/O$79 -> 0.59234677 | P84: =P83/P$79 -> 0.59542211 | R84: =IF($R$5=1,_xlfn.FORMULATEXT(P84),"")
D85: EBITDA growth rate | E85: % | I85: =IFERROR(I83/H83-1,0) -> 0 | J85: =IFERROR(J83/I83-1,0) -> 0.04 | K85: =IFERROR(K83/J83-1,0) -> 0.051061008 | L85: =IFERROR(L83/K83-1,0) -> 0.084549769 | M85: =IFERROR(M83/L83-1,0) -> 0.12359899 | N85: =IFERROR(N83/M83-1,0) -> 0.11580193 | O85: =IFERROR(O83/N83-1,0) -> 0.10920401 | P85: =IFERROR(P83/O83-1,0) -> 0.054516118 | R85: =IF($R$5=1,_xlfn.FORMULATEXT(P85),"")
C87: Net Income
D88: Net Income | E88: $MM | I88: =Model!I31 -> 48.1 | J88: =Model!J31 -> 45.5 | K88: =Model!K31 -> 43.1 | L88: =Model!L31 -> 46.07475 | M88: =Model!M31 -> 56.659288 | N88: =Model!N31 -> 73.021245 | O88: =Model!O31 -> 89.417688 | P88: =Model!P31 -> 97.597577 | R88: =IF($R$5=1,_xlfn.FORMULATEXT(P88),"")
D89: Net Income Margin | E89: % | I89: =I88/I$79 -> 0.20546775 | J89: =J88/J$79 -> 0.1758794 | K89: =K88/K$79 -> 0.15453568 | L89: =L88/L$79 -> 0.14970035 | M89: =M88/M$79 -> 0.16756089 | N89: =N88/N$79 -> 0.19732922 | O89: =O88/O$79 -> 0.22156994 | P89: =P88/P$79 -> 0.23052718 | R89: =IF($R$5=1,_xlfn.FORMULATEXT(P89),"")
D90: Net Income Growth rate | E90: % | I90: =IFERROR(I88/H88-1,0) -> 0 | J90: =IFERROR(J88/I88-1,0) -> -0.054054054 | K90: =IFERROR(K88/J88-1,0) -> -0.052747253 | L90: =IFERROR(L88/K88-1,0) -> 0.069019715 | M90: =IFERROR(M88/L88-1,0) -> 0.22972535 | N90: =IFERROR(N88/M88-1,0) -> 0.28877802 | O90: =IFERROR(O88/N88-1,0) -> 0.22454347 | P90: =IFERROR(P88/O88-1,0) -> 0.091479538 | R90: =IF($R$5=1,_xlfn.FORMULATEXT(P90),"")
C92: Dupont Analysis
D93: Return on Equity | E93: % | I93: =Model!I38 -> 0.026125686 | J93: =Model!J38 -> 0.024274434 | K93: =Model!K38 -> 0.022659166 | L93: =Model!L38 -> 0.023891508 | M93: =Model!M38 -> 0.010547263 | N93: =Model!N38 -> 0.0032863002 | O93: =Model!O38 -> 0.0091920335 | P93: =Model!P38 -> 0.012034685 | R93: =IF($R$5=1,_xlfn.FORMULATEXT(P93),"")
D94: Net Profit Margin | E94: % | I94: =Model!I39 -> 0.20546775 | J94: =Model!J39 -> 0.1758794 | K94: =Model!K39 -> 0.15453568 | L94: =Model!L39 -> 0.14970035 | M94: =Model!M39 -> 0.16756089 | N94: =Model!N39 -> 0.19732922 | O94: =Model!O39 -> 0.22156994 | P94: =Model!P39 -> 0.23052718 | R94: =IF($R$5=1,_xlfn.FORMULATEXT(P94),"")
D95: Asset Turnover | E95: Multiple | I95: =Model!I40 -> 0.089157177 | J95: =Model!J40 -> 0.094967145 | K95: =Model!K40 -> 0.099182077 | L95: =Model!L40 -> 0.11417627 | M95: =Model!M40 -> 0.11719452 | N95: =Model!N40 -> 0.11892624 | O95: =Model!O40 -> 0.13676314 | P95: =Model!P40 -> 0.14357879 | R95: =IF($R$5=1,_xlfn.FORMULATEXT(P95),"")
D96: Financial Leverage | E96: Multiple | I96: =Model!I41 -> 1.4261583 | J96: =Model!J41 -> 1.4533184 | K96: =Model!K41 -> 1.478366 | L96: =Model!L41 -> 1.3977996 | M96: =Model!M41 -> 1.2341 | N96: =Model!N41 -> 1.1334984 | O96: =Model!O41 -> 1.0671344 | P96: =Model!P41 -> 1.0562176 | R96: =IF($R$5=1,_xlfn.FORMULATEXT(P96),"")

Sheet Assumptions
B2: =Cover!B4 -> Xcel Stores & Properties
C3: Assumptions | I3: =IF(BalCheck=0,"Bal check: OK","ERROR") -> Bal check: OK | K3: {="Scenario: "&INDEX(S_List,S_Scenario)} -> Scenario: Base Case
I4: Actual | J4: Actual | K4: Actual | L4: Forecast | M4: Forecast | N4: Forecast | O4: Forecast | P4: Forecast
E5: units | F5: Inputs/drivers | I5: =Historical!G7 -> 2020 | J5: =I5+1 -> 2021 | K5: =J5+1 -> 2022 | L5: =K5+1 -> 2023 | M5: =L5+1 -> 2024 | N5: =M5+1 -> 2025 | O5: =N5+1 -> 2026 | P5: =O5+1 -> 2027
B7: General Assumptions
D8: Days in the period | E8: Days | I8: =DATE(I5,12,31)-DATE(I5,1,1)+1 -> 366 | J8: =DATE(J5,12,31)-DATE(J5,1,1)+1 -> 365 | K8: =DATE(K5,12,31)-DATE(K5,1,1)+1 -> 365 | L8: =DATE(L5,12,31)-DATE(L5,1,1)+1 -> 365 | M8: =DATE(M5,12,31)-DATE(M5,1,1)+1 -> 366 | N8: =DATE(N5,12,31)-DATE(N5,1,1)+1 -> 365 | O8: =DATE(O5,12,31)-DATE(O5,1,1)+1 -> 365 | P8: =DATE(P5,12,31)-DATE(P5,1,1)+1 -> 365
D9: Million | E9: Constant | F9: 1000000
B11: Styles
D12: Normal Style | E12: Number | F12: 123456
D13: Input Style | E13: Number | F13: 123456
D14: Percent Style | E14: Percent | F14: 0.12
D15: Linked Cell Style | E15: Number | F15: 123
D16: Heading | E16: Text | F16: Heading
D17: Explanatory | E17: Text | F17: Text
D18: Multiple | E18: Number | F18: 12
B20: Revenue Assumption
C22: Sales Volume
D23: Total Numbers of Properties | E23: unit | K23: 390
D24: Current Leasable Areas | E24: Square feet | K24: 1560000
D25: Land currently Built up | E25: % | K25: 0.6
D26: Land available for new property | E26: % | K26: 0.2
D28: Additional Properties Assumption | E28: unit | L28: =Scenario!L34 -> 30 | M28: =Scenario!M34 -> 30 | N28: =Scenario!N34 -> 30 | O28: =Scenario!O34 -> 30 | P28: =Scenario!P34 -> 30
C30: Sales Price
D31: Rent growth | E31: % | L31: =Scenario!L26 -> 0.03 | M31: =Scenario!M26 -> 0.03 | N31: =Scenario!N26 -> 0.03 | O31: =Scenario!O26 -> 0.03 | P31: =Scenario!P26 -> 0.03
D33: Auxilliary Income | E33: $'MM | K33: 20
D34: Inflation | E34: % | L34: =Scenario!L18 -> 0.03 | M34: =Scenario!M18 -> 0.03 | N34: =Scenario!N18 -> 0.03 | O34: =Scenario!O18 -> 0.03 | P34: =Scenario!P18 -> 0.03
B36: Operating Cost Assumption
C37: Cost of Sales [%]
D38: Variable Cost | E38: % | K38: 0.6
D39: Fixed Cost | E39: % | K39: =1-K38 -> 0.4
D40: Total | E40: % | K40: =SUM(K38:K39) -> 1
D42: Selling, General & Administrative Expenses | E42: $'MM | L42: 25
B44: CAPEX & Depreciation Assumption
D46: CAPEX Addition | E46: $'MM | L46: 140 | M46: 140 | N46: 150 | O46: 150 | P46: 150
D47: Depreciation Method | E47: Declining Balance Method
C49: Useful Life
D50: Existing Assets | E50: Years | F50: 0.02
D51: New Assets | E51: Years | F51: 0.1
B54: Working Capital Assumption
D56: =D8 -> Days in the period | E56: =E8 -> Days | I56: =I8 -> 366 | J56: =J8 -> 365 | K56: =K8 -> 365 | L56: =L8 -> 365 | M56: =M8 -> 366 | N56: =N8 -> 365 | O56: =O8 -> 365 | P56: =P8 -> 365
C57: Extracts from the Financials
D58: =Historical!C13 -> Revenue | E58: $'MM | I58: =Historical!G13 -> 234.1 | J58: =Historical!H13 -> 258.7 | K58: =Historical!I13 -> 278.9
D59: =Historical!C15 -> Operating Costs | E59: $'MM | I59: =Historical!G15 -> 74.6 | J59: =Historical!H15 -> 91.8 | K59: =Historical!I15 -> 102.9
C61: Current Assets [$]
D62: =Historical!C88 -> Accounts Receivable | E62: $'MM | I62: =Historical!G88 -> 16 | J62: =Historical!H88 -> 15.1 | K62: =Historical!I88 -> 20.2
D63: =Historical!C89 -> Inventory | E63: $'MM | I63: =Historical!G89 -> 2.8 | J63: =Historical!H89 -> 3.6 | K63: =Historical!I89 -> 4.2
D64: =Historical!C90 -> Other Current Assets | E64: $'MM | I64: =Historical!G90 -> 0.3 | J64: =Historical!H90 -> 0.2 | K64: =Historical!I90 -> 0.2
C66: Current Liabilities [$]
D67: =Historical!C104 -> Accounts Payable | E67: $'MM | I67: =Historical!G104 -> 14.9 | J67: =Historical!H104 -> 21.5 | K67: =Historical!I104 -> 23.9
D68: =Historical!C105 -> Other Current Liabilities | E68: $'MM | I68: =Historical!G105 -> 4.6 | J68: =Historical!H105 -> 5.1 | K68: =Historical!I105 -> 4.9
C70: Current Assets [days]
D71: Accounts Receivable | E71: days | I71: =I62/I58*I56 -> 25.014951 | J71: =J62/J58*J56 -> 21.3046 | K71: =K62/K58*K56 -> 26.435999 | L71: 24.25 | M71: 24.25 | N71: 24.25 | O71: 24.25 | P71: 24.25
D72: Inventory | E72: days | I72: =I63/I$59*I$56 -> 13.737265 | J72: =J63/J$59*J$56 -> 14.313725 | K72: =K63/K$59*K$56 -> 14.897959 | L72: 14.32 | M72: 14.32 | N72: 14.32 | O72: 14.32 | P72: 14.32
D73: Other Current Assets | E73: days | I73: =I64/I$59*I$56 -> 1.4718499 | J73: =J64/J$59*J$56 -> 0.79520697 | K73: =K64/K$59*K$56 -> 0.70942663 | L73: 0.99 | M73: 0.99 | N73: 0.99 | O73: 0.99 | P73: 0.99
C75: Current Liabilities [days]
D76: Accounts Payable | E76: days | I76: =I67/I$59*I$56 -> 73.101877 | J76: =J67/J$59*J$56 -> 85.484749 | K76: =K67/K$59*K$56 -> 84.776482 | L76: 81.12 | M76: 81.12 | N76: 81.12 | O76: 81.12 | P76: 81.12
D77: Other Current Liabilities | E77: days | I77: =I68/I$59*I$56 -> 22.568365 | J77: =J68/J$59*J$56 -> 20.277778 | K77: =K68/K$59*K$56 -> 17.380952 | L77: 20.08 | M77: 20.08 | N77: 20.08 | O77: 20.08 | P77: 20.08
B79: Income Tax Assumption
D81: Company Tax Rate | E81: % | F81: 0.325
D82: Reduction due to timing difference | E82: $'MM | L82: 5 | M82: 5 | N82: 5 | O82: 5 | P82: 5
B84: Debt Assumption
C86: Interest Rates
D87: Fixed Rate Longterm Debt | E87: % | F87: 0.065
D88: Revolver | E88: % | F88: 0.055
D90: Variable Rate longterm debt
D91: Interest at a variable rate | E91: % | F91: 0.0225
D92: SOFR Benchmark Rate | E92: % | F92: 0.03
D93: Interest Rate on Variable rate longterm debt | E93: % | F93: =SUM(F91:F92) -> 0.0525
D95: Excess Cash | E95: % | F95: 0.0075
D97: Amortization on fixed rate longterm debt | E97: $'MM | L97: 50 | M97: 50 | N97: 50 | O97: 50 | P97: 50
D98: Amortization on Variable rate longterm debts | E98: $'MM | L98: 135 | M98: 135 | N98: 135 | O98: 135 | P98: 135
D99: The Company will draw on its revolver if it ever has a cash shortfall.
B102: Equity Assumption
C104: Common Shares
D105: Common Shares: Issuance/(Buyback) | E105: $'MM | L105: -10 | M105: -10 | N105: 0 | O105: 0 | P105: 0
D106: Dividend Payout ratio | E106: % | F106: 0.21
C108: Preference Shares
D109: Preference Shares: Issuance/(Buyback) | E109: $'MM | L109: 0 | M109: 400 | N109: 400 | O109: 0 | P109: 0
D110: Dividend Yield | E110: % | F110: 0.08
B112: Other Assumptions
D114: Cost Adjustments - Gain / (Loss) | E114: $'MM | L114: 0 | M114: 0 | N114: 0 | O114: 0 | P114: 0
D115: =Historical!C25 -> Foreign Exchange - Gain / (Loss) | E115: $'MM | L115: 0 | M115: 0 | N115: 0 | O115: 0 | P115: 0
D116: Other Operating Activities | E116: $'MM | L116: 0 | M116: 0 | N116: 0 | O116: 0 | P116: 0
D117: Other Investing Activities | E117: $'MM | L117: 0 | M117: 0 | N117: 0 | O117: 0 | P117: 0
D118: Assets diposition | E118: $'MM | L118: 0 | M118: 0 | N118: 0 | O118: 0 | P118: 0
D119: Other Financing Activities | E119: $'MM | L119: 0 | M119: 0 | N119: 0 | O119: 0 | P119: 0
D120: Goodwill | E120: $'MM | L120: 0 | M120: 0 | N120: 0 | O120: 0 | P120: 0
D121: Intangibles | E121: $'MM | L121: 0 | M121: 0 | N121: 0 | O121: 0 | P121: 0
D122: Other Long term Assets | E122: $'MM | L122: 0 | M122: 0 | N122: 0 | O122: 0 | P122: 0
D123: Other Long term Liabilities | E123: $'MM | L123: 0 | M123: 0 | N123: 0 | O123: 0 | P123: 0
D124: Other Shareholders Equity | E124: $'MM | L124: 0 | M124: 0 | N124: 0 | O124: 0 | P124: 0

Sheet Scenario
B2: =Cover!B4 -> Xcel Stores & Properties
C3: Scenario Analysis | I3: =IF(BalCheck=0,"Bal check: OK","ERROR") -> Bal check: OK | K3: {="Scenario: "&INDEX(S_List,S_Scenario)} -> Scenario: Base Case
I4: Actual | J4: Actual | K4: Actual | L4: Forecast | M4: Forecast | N4: Forecast | O4: Forecast | P4: Forecast
E5: units | F5: Inputs/drivers | I5: =Historical!G7 -> 2020 | J5: =I5+1 -> 2021 | K5: =J5+1 -> 2022 | L5: =K5+1 -> 2023 | M5: =L5+1 -> 2024 | N5: =M5+1 -> 2025 | O5: =N5+1 -> 2026 | P5: =O5+1 -> 2027
B7: {="Scenario Analysis "&INDEX(S_List,S_Scenario)} -> Scenario Analysis Base Case
D9: Scenario Switch>>>> | F9: 1
C11: Scenario List
D12: Base Case
D13: Best Case
D14: Worst Case
B16: Inflation Scenario
D18: Used in the Model | L18: {=INDEX(L20:L22,S_Scenario)} -> 0.03 | M18: {=INDEX(M20:M22,S_Scenario)} -> 0.03 | N18: {=INDEX(N20:N22,S_Scenario)} -> 0.03 | O18: {=INDEX(O20:O22,S_Scenario)} -> 0.03 | P18: {=INDEX(P20:P22,S_Scenario)} -> 0.03
D20: Base Case | E20: % | L20: 0.03 | M20: 0.03 | N20: 0.03 | O20: 0.03 | P20: 0.03
D21: Best Case | E21: % | L21: 0.02 | M21: 0.02 | N21: 0.02 | O21: 0.02 | P21: 0.02
D22: Worst Case | E22: % | L22: 0.04 | M22: 0.04 | N22: 0.04 | O22: 0.04 | P22: 0.04
B24: Rent Growth Scenario
D26: Used in the Model | L26: {=INDEX(L28:L30,S_Scenario)} -> 0.03 | M26: {=INDEX(M28:M30,S_Scenario)} -> 0.03 | N26: {=INDEX(N28:N30,S_Scenario)} -> 0.03 | O26: {=INDEX(O28:O30,S_Scenario)} -> 0.03 | P26: {=INDEX(P28:P30,S_Scenario)} -> 0.03
D28: Base Case | E28: % | L28: 0.03 | M28: 0.03 | N28: 0.03 | O28: 0.03 | P28: 0.03
D29: Best Case | E29: % | L29: 0.04 | M29: 0.04 | N29: 0.04 | O29: 0.04 | P29: 0.04
D30: Worst Case | E30: % | L30: 0.02 | M30: 0.04 | N30: 0.04 | O30: 0.04 | P30: 0.04
B32: Additional Properties Scenario
D34: Used in the Model | L34: {=INDEX(L36:L38,S_Scenario)} -> 30 | M34: {=INDEX(M36:M38,S_Scenario)} -> 30 | N34: {=INDEX(N36:N38,S_Scenario)} -> 30 | O34: {=INDEX(O36:O38,S_Scenario)} -> 30 | P34: {=INDEX(P36:P38,S_Scenario)} -> 30
D36: Base Case | E36: units | L36: 30 | M36: 30 | N36: 30 | O36: 30 | P36: 30
D37: Best Case | E37: units | L37: 35 | M37: 35 | N37: 35 | O37: 35 | P37: 35
D38: Worst Case | E38: units | L38: 25 | M38: 25 | N38: 25 | O38: 25 | P38: 25

Sheet Model
B2: =Cover!B4 -> Xcel Stores & Properties
C3: Model | I3: =IF(BalCheck=0,"Bal check: OK","ERROR") -> Bal check: OK | K3: {="Scenario: "&INDEX(S_List,S_Scenario)} -> Scenario: Base Case
I4: Actual | J4: Actual | K4: Actual | L4: Forecast | M4: Forecast | N4: Forecast | O4: Forecast | P4: Forecast
E5: units | F5: Inputs/drivers | I5: =Historical!G7 -> 2020 | J5: =I5+1 -> 2021 | K5: =J5+1 -> 2022 | L5: =K5+1 -> 2023 | M5: =L5+1 -> 2024 | N5: =M5+1 -> 2025 | O5: =N5+1 -> 2026 | P5: =O5+1 -> 2027 | R5: 2
B7: Financial Statements
C9: Income Statements
D11: =Historical!C13 -> Revenue | E11: $'MM | I11: =Historical!G13 -> 234.1 | J11: =Historical!H13 -> 258.7 | K11: =Historical!I13 -> 278.9 | L11: =L155 -> 307.77985 | M11: =M155 -> 338.14147 | N11: =N155 -> 370.0478 | O11: =O155 -> 403.56417 | P11: =P155 -> 423.36689 | R11: =IF($R$5=1,_xlfn.FORMULATEXT(P11),"")
D13: =Historical!C15 -> Operating Costs | E13: $'MM | I13: =Historical!G15 -> 74.6 | J13: =Historical!H15 -> 91.8 | K13: =Historical!I15 -> 102.9 | L13: =L175 -> 110.87871 | M13: =M175 -> 119.24353 | N13: =N175 -> 128.01045 | O13: =O175 -> 137.19606 | P13: =P175 -> 143.14716 | R13: =IF($R$5=1,_xlfn.FORMULATEXT(P13),"")
D14: =Historical!C16 -> SG&A | E14: $'MM | I14: =Historical!G16 -> 14.5 | J14: =Historical!H16 -> 16.9 | K14: =Historical!I16 -> 19.8 | L14: =L177 -> 25 | M14: =M177 -> 25.75 | N14: =N177 -> 26.5225 | O14: =O177 -> 27.318175 | P14: =P177 -> 28.13772 | R14: =IF($R$5=1,_xlfn.FORMULATEXT(P14),"")
D15: =Historical!C17 -> Total Costs | E15: $'MM | I15: =I13+I14 -> 89.1 | J15: =J13+J14 -> 108.7 | K15: =K13+K14 -> 122.7 | L15: =L13+L14 -> 135.87871 | M15: =M13+M14 -> 144.99353 | N15: =N13+N14 -> 154.53295 | O15: =O13+O14 -> 164.51424 | P15: =P13+P14 -> 171.28488 | R15: =IF($R$5=1,_xlfn.FORMULATEXT(P15),"")
D17: =Historical!C19 -> Cost Adjustments - Gain / (Loss) | E17: $'MM | I17: =Historical!G19 -> 0 | J17: =Historical!H19 -> 0.8 | K17: =Historical!I19 -> 2.3 | L17: =Assumptions!L114 -> 0 | M17: =Assumptions!M114 -> 0 | N17: =Assumptions!N114 -> 0 | O17: =Assumptions!O114 -> 0 | P17: =Assumptions!P114 -> 0 | R17: =IF($R$5=1,_xlfn.FORMULATEXT(P17),"")
D18: =Historical!C20 -> EBITDA | E18: $'MM | I18: =I11-I15+I17 -> 145 | J18: =J11-J15+J17 -> 150.8 | K18: =K11-K15+K17 -> 158.5 | L18: =L11-L15+L17 -> 171.90114 | M18: =M11-M15+M17 -> 193.14795 | N18: =N11-N15+N17 -> 215.51485 | O18: =O11-O15+O17 -> 239.04993 | P18: =P11-P15+P17 -> 252.08201 | R18: =IF($R$5=1,_xlfn.FORMULATEXT(P18),"")
D20: =Historical!C22 -> Depreciation | E20: $'MM | I20: =Historical!G22 -> 41.7 | J20: =Historical!H22 -> 46.2 | K20: =Historical!I22 -> 54.6 | L20: =L246 -> 57.844 | M20: =M246 -> 70.12712 | N20: =N246 -> 81.600578 | O20: =O246 -> 92.346966 | P20: =P246 -> 101.94059 | R20: =IF($R$5=1,_xlfn.FORMULATEXT(P20),"")
D21: =Historical!C23 -> EBIT | E21: $'MM | I21: =I18-I20 -> 103.3 | J21: =J18-J20 -> 104.6 | K21: =K18-K20 -> 103.9 | L21: =L18-L20 -> 114.05714 | M21: =M18-M20 -> 123.02083 | N21: =N18-N20 -> 133.91427 | O21: =O18-O20 -> 146.70297 | P21: =P18-P20 -> 150.14142 | R21: =IF($R$5=1,_xlfn.FORMULATEXT(P21),"")
D23: =Historical!C25 -> Foreign Exchange - Gain / (Loss) | E23: $'MM | I23: =Historical!G25 -> 0 | J23: =Historical!H25 -> -2.6 | K23: =Historical!I25 -> 0 | L23: =Assumptions!L115 -> 0 | M23: =Assumptions!M115 -> 0 | N23: =Assumptions!N115 -> 0 | O23: =Assumptions!O115 -> 0 | P23: =Assumptions!P115 -> 0 | R23: =IF($R$5=1,_xlfn.FORMULATEXT(P23),"")
D24: =Historical!C26 -> Net Interest Expense | E24: $'MM | I24: =Historical!G26 -> 33.5 | J24: =Historical!H26 -> 34.2 | K24: =Historical!I26 -> 36.6 | L24: =L383 -> 45.79825 | M24: =M383 -> 39.08114 | N24: =N383 -> 25.73465 | O24: =O383 -> 14.232319 | P24: =P383 -> 5.552419 | R24: =IF($R$5=1,_xlfn.FORMULATEXT(P24),"")
D25: =Historical!C27 -> EBT | E25: $'MM | I25: =I21+I23-I24 -> 69.8 | J25: =J21+J23-J24 -> 67.8 | K25: =K21+K23-K24 -> 67.3 | L25: =L21+L23-L24 -> 68.258888 | M25: =M21+M23-M24 -> 83.939686 | N25: =N21+N23-N24 -> 108.17962 | O25: =O21+O23-O24 -> 132.47065 | P25: =P21+P23-P24 -> 144.589 | R25: =IF($R$5=1,_xlfn.FORMULATEXT(P25),"")
D27: =Historical!C29 -> Current Taxes | E27: $'MM | I27: =Historical!G29 -> 11.3 | J27: =Historical!H29 -> 10.5 | K27: =Historical!I29 -> 15.8 | L27: =L294 -> 20.559139 | M27: =M294 -> 25.655398 | N27: =N294 -> 33.533377 | O27: =O294 -> 41.427961 | P27: =P294 -> 45.366426 | R27: =IF($R$5=1,_xlfn.FORMULATEXT(P27),"")
D28: =Historical!C30 -> Deferred Income Taxes | E28: $'MM | I28: =Historical!G30 -> 10.4 | J28: =Historical!H30 -> 11.8 | K28: =Historical!I30 -> 8.4 | L28: =L295 -> 1.625 | M28: =M295 -> 1.625 | N28: =N295 -> 1.625 | O28: =O295 -> 1.625 | P28: =P295 -> 1.625 | R28: =IF($R$5=1,_xlfn.FORMULATEXT(P28),"")
D29: =Historical!C31 -> Total Income Taxes | E29: $'MM | I29: =SUM(I27:I28) -> 21.7 | J29: =SUM(J27:J28) -> 22.3 | K29: =SUM(K27:K28) -> 24.2 | L29: =SUM(L27:L28) -> 22.184139 | M29: =SUM(M27:M28) -> 27.280398 | N29: =SUM(N27:N28) -> 35.158377 | O29: =SUM(O27:O28) -> 43.052961 | P29: =SUM(P27:P28) -> 46.991426 | R29: =IF($R$5=1,_xlfn.FORMULATEXT(P29),"")
D31: =Historical!C33 -> Net Income | E31: $'MM | I31: =I25-I29 -> 48.1 | J31: =J25-J29 -> 45.5 | K31: =K25-K29 -> 43.1 | L31: =L25-L29 -> 46.07475 | M31: =M25-M29 -> 56.659288 | N31: =N25-N29 -> 73.021245 | O31: =O25-O29 -> 89.417688 | P31: =P25-P29 -> 97.597577 | R31: =IF($R$5=1,_xlfn.FORMULATEXT(P31),"")
D33: =Historical!C35 -> Preferred Dividend | E33: $'MM | I33: =Historical!G35 -> 0 | J33: =Historical!H35 -> 0 | K33: =Historical!I35 -> 0 | L33: =L318 -> 0 | M33: =M318 -> 32 | N33: =N318 -> 64 | O33: =O318 -> 64 | P33: =P318 -> 64 | R33: =IF($R$5=1,_xlfn.FORMULATEXT(P33),"")
D34: =Historical!C36 -> Net Income to Common | E34: $'MM | I34: =I31-I33 -> 48.1 | J34: =J31-J33 -> 45.5 | K34: =K31-K33 -> 43.1 | L34: =L31-L33 -> 46.07475 | M34: =M31-M33 -> 24.659288 | N34: =N31-N33 -> 9.0212445 | O34: =O31-O33 -> 25.417688 | P34: =P31-P33 -> 33.597577 | R34: =IF($R$5=1,_xlfn.FORMULATEXT(P34),"")
D36: EBITDA Margin | E36: % | I36: =I18/I11 -> 0.61939342 | J36: =J18/J11 -> 0.58291457 | K36: =K18/K11 -> 0.56830405 | L36: =L18/L11 -> 0.5585198 | M36: =M18/M11 -> 0.57120454 | N36: =N18/N11 -> 0.58239733 | O36: =O18/O11 -> 0.59234677 | P36: =P18/P11 -> 0.59542211 | R36: =IF($R$5=1,_xlfn.FORMULATEXT(P36),"")
C37: Dupont Analysis
D38: Return on Equity | E38: % | I38: =I34/I111 -> 0.026125686 | J38: =J34/J111 -> 0.024274434 | K38: =K34/K111 -> 0.022659166 | L38: =L34/L111 -> 0.023891508 | M38: =M34/M111 -> 0.010547263 | N38: =N34/N111 -> 0.0032863002 | O38: =O34/O111 -> 0.0091920335 | P38: =P34/P111 -> 0.012034685 | R38: =IF($R$5=1,_xlfn.FORMULATEXT(P38),"")
D39: Net Profit Margin | E39: % | I39: =I31/I11 -> 0.20546775 | J39: =J31/J11 -> 0.1758794 | K39: =K31/K11 -> 0.15453568 | L39: =L31/L11 -> 0.14970035 | M39: =M31/M11 -> 0.16756089 | N39: =N31/N11 -> 0.19732922 | O39: =O31/O11 -> 0.22156994 | P39: =P31/P11 -> 0.23052718 | R39: =IF($R$5=1,_xlfn.FORMULATEXT(P39),"")
D40: Asset Turnover | E40: Multiple | I40: =I11/I90 -> 0.089157177 | J40: =J11/J90 -> 0.094967145 | K40: =K11/K90 -> 0.099182077 | L40: =L11/L90 -> 0.11417627 | M40: =M11/M90 -> 0.11719452 | N40: =N11/N90 -> 0.11892624 | O40: =O11/O90 -> 0.13676314 | P40: =P11/P90 -> 0.14357879 | R40: =IF($R$5=1,_xlfn.FORMULATEXT(P40),"")
D41: Financial Leverage | E41: Multiple | I41: =I90/I111 -> 1.4261583 | J41: =J90/J111 -> 1.4533184 | K41: =K90/K111 -> 1.478366 | L41: =L90/L111 -> 1.3977996 | M41: =M90/M111 -> 1.2341 | N41: =N90/N111 -> 1.1334984 | O41: =O90/O111 -> 1.0671344 | P41: =P90/P111 -> 1.0562176 | R41: =IF($R$5=1,_xlfn.FORMULATEXT(P41),"")
C44: Cashflow Statements
C46: =Historical!B48 -> Operating Activities
D47: =Historical!C49 -> Net Income | E47: $'MM | I47: =I31 -> 48.1 | J47: =J31 -> 45.5 | K47: =K31 -> 43.1 | L47: =L31 -> 46.07475 | M47: =M31 -> 56.659288 | N47: =N31 -> 73.021245 | O47: =O31 -> 89.417688 | P47: =P31 -> 97.597577 | R47: =IF($R$5=1,_xlfn.FORMULATEXT(P47),"")
D48: =Historical!C50 -> Depreciation | E48: $'MM | I48: =Historical!G50 -> 41.7 | J48: =Historical!H50 -> 46.2 | K48: =Historical!I50 -> 54.6 | L48: =L20 -> 57.844 | M48: =M20 -> 70.12712 | N48: =N20 -> 81.600578 | O48: =O20 -> 92.346966 | P48: =P20 -> 101.94059 | R48: =IF($R$5=1,_xlfn.FORMULATEXT(P48),"")
D49: =Historical!C51 -> Deferred Income Taxes | E49: $'MM | I49: =Historical!G51 -> 10.4 | J49: =Historical!H51 -> 11.8 | K49: =Historical!I51 -> 8.4 | L49: =L28 -> 1.625 | M49: =M28 -> 1.625 | N49: =N28 -> 1.625 | O49: =O28 -> 1.625 | P49: =P28 -> 1.625 | R49: =IF($R$5=1,_xlfn.FORMULATEXT(P49),"")
D50: =Historical!C52 -> Changes in Working Capital | E50: $'MM | I50: =Historical!G52 -> 2.4 | J50: =Historical!H52 -> 6.7 | K50: =Historical!I52 -> -3.3 | L50: =L280 -> 1.4430437 | M50: =M280 -> -0.064093152 | N50: =N280 -> -0.041530801 | O50: =O280 -> -0.065259344 | P50: =P280 -> 0.08472368 | R50: =IF($R$5=1,_xlfn.FORMULATEXT(P50),"")
D51: =Historical!C53 -> Other | E51: $'MM | I51: =Historical!G53 -> 0.4 | J51: =Historical!H53 -> -0.4 | K51: =Historical!I53 -> -0.3 | L51: =Assumptions!L116 -> 0 | M51: =Assumptions!M116 -> 0 | N51: =Assumptions!N116 -> 0 | O51: =Assumptions!O116 -> 0 | P51: =Assumptions!P116 -> 0 | R51: =IF($R$5=1,_xlfn.FORMULATEXT(P51),"")
D52: =Historical!C54 -> Operating Cash Flow | E52: $'MM | I52: =SUM(I47:I51) -> 103 | J52: =SUM(J47:J51) -> 109.8 | K52: =SUM(K47:K51) -> 102.5 | L52: =SUM(L47:L51) -> 106.98679 | M52: =SUM(M47:M51) -> 128.34731 | N52: =SUM(N47:N51) -> 156.20529 | O52: =SUM(O47:O51) -> 183.3244 | P52: =SUM(P47:P51) -> 201.24789 | R52: =IF($R$5=1,_xlfn.FORMULATEXT(P52),"")
C54: =Historical!B57 -> Investing Activities
D55: =Historical!C58 -> CAPEX | E55: $'MM | I55: =Historical!G58 -> -121.1 | J55: =Historical!H58 -> -159.7 | K55: =Historical!I58 -> -151.2 | L55: =-L245 -> -140 | M55: =-M245 -> -140 | N55: =-N245 -> -150 | O55: =-O245 -> -150 | P55: =-P245 -> -150 | R55: =IF($R$5=1,_xlfn.FORMULATEXT(P55),"")
D56: =Historical!C59 -> Asset Dispositions | E56: $'MM | I56: =Historical!G59 -> 23.4 | J56: =Historical!H59 -> 13.8 | K56: =Historical!I59 -> 5.8 | L56: =Assumptions!L118 -> 0 | M56: =Assumptions!M118 -> 0 | N56: =Assumptions!N118 -> 0 | O56: =Assumptions!O118 -> 0 | P56: =Assumptions!P118 -> 0 | R56: =IF($R$5=1,_xlfn.FORMULATEXT(P56),"")
D57: =Historical!C60 -> Other | E57: $'MM | I57: =Historical!G60 -> 2.5 | J57: =Historical!H60 -> 2.6 | K57: =Historical!I60 -> 0.8 | L57: =Assumptions!L117 -> 0 | M57: =Assumptions!M117 -> 0 | N57: =Assumptions!N117 -> 0 | O57: =Assumptions!O117 -> 0 | P57: =Assumptions!P117 -> 0 | R57: =IF($R$5=1,_xlfn.FORMULATEXT(P57),"")
D58: =Historical!C61 -> Investing Cash Flow | E58: $'MM | I58: =SUM(I55:I57) -> -95.2 | J58: =SUM(J55:J57) -> -143.3 | K58: =SUM(K55:K57) -> -144.6 | L58: =SUM(L55:L57) -> -140 | M58: =SUM(M55:M57) -> -140 | N58: =SUM(N55:N57) -> -150 | O58: =SUM(O55:O57) -> -150 | P58: =SUM(P55:P57) -> -150 | R58: =IF($R$5=1,_xlfn.FORMULATEXT(P58),"")
C60: =Historical!B64 -> Financing Activities
D61: =Historical!C65 -> Revolver Issuance / (Repayment) | E61: $'MM | I61: =Historical!G65 -> 0 | J61: =Historical!H65 -> 0 | K61: =Historical!I65 -> 0 | L61: =L373 -> 38.688904 | M61: =M373 -> -38.688904 | N61: =N373 -> 0 | O61: =O373 -> 0 | P61: =P373 -> 75.330133 | R61: =IF($R$5=1,_xlfn.FORMULATEXT(P61),"")
D62: =Historical!C66 -> Variable Rate Long Term Debt Issuance / (Repayment) | E62: $'MM | I62: =Historical!G66 -> -26 | J62: =Historical!H66 -> 20 | K62: =Historical!I66 -> 25 | L62: =-L343 -> -135 | M62: =-M343 -> -135 | N62: =-N343 -> -135 | O62: =-O343 -> -135 | P62: =-P343 -> -82.7 | R62: =IF($R$5=1,_xlfn.FORMULATEXT(P62),"")
D63: =Historical!C67 -> Fixed Rate Long Term Debt Issuance / (Repayment) | E63: $'MM | I63: =Historical!G67 -> 5 | J63: =Historical!H67 -> 25 | K63: =Historical!I67 -> 25 | L63: =-L333 -> -50 | M63: =-M333 -> -50 | N63: =-N333 -> -50 | O63: =-O333 -> -50 | P63: =-P333 -> -24.6 | R63: =IF($R$5=1,_xlfn.FORMULATEXT(P63),"")
D64: =Historical!C68 -> Preferred Share Issuance / (Buy-Back) | E64: $'MM | I64: =Historical!G68 -> 0 | J64: =Historical!H68 -> 0 | K64: =Historical!I68 -> 0 | L64: =L315 -> 0 | M64: =M315 -> 400 | N64: =N315 -> 400 | O64: =O315 -> 0 | P64: =P315 -> 0 | R64: =IF($R$5=1,_xlfn.FORMULATEXT(P64),"")
D65: =Historical!C69 -> Common Share Issuance / (Buy-Back) | E65: $'MM | I65: =Historical!G69 -> -5 | J65: =Historical!H69 -> -4 | K65: =Historical!I69 -> -6 | L65: =L307 -> -10 | M65: =M307 -> -10 | N65: =N307 -> 0 | O65: =O307 -> 0 | P65: =P307 -> 0 | R65: =IF($R$5=1,_xlfn.FORMULATEXT(P65),"")
D66: =Historical!C70 -> Preferred Share Dividends | E66: $'MM | I66: =Historical!G70 -> 0 | J66: =Historical!H70 -> 0 | K66: =Historical!I70 -> 0 | L66: =-L318 -> 0 | M66: =-M318 -> -32 | N66: =-N318 -> -64 | O66: =-O318 -> -64 | P66: =-P318 -> -64 | R66: =IF($R$5=1,_xlfn.FORMULATEXT(P66),"")
D67: =Historical!C71 -> Common Share Dividends | E67: $'MM | I67: =Historical!G71 -> -7.2 | J67: =Historical!H71 -> -9.6 | K67: =Historical!I71 -> -9.1 | L67: =-L323 -> -9.6756974 | M67: =-M323 -> -5.1784504 | N67: =-N323 -> -1.8944613 | O67: =-O323 -> -5.3377146 | P67: =-P323 -> -7.0554912 | R67: =IF($R$5=1,_xlfn.FORMULATEXT(P67),"")
D68: =Historical!C72 -> Other | E68: $'MM | I68: =Historical!G72 -> 0.8 | J68: =Historical!H72 -> 0.6 | K68: =Historical!I72 -> -0.5 | L68: =Assumptions!L122 -> 0 | M68: =Assumptions!M122 -> 0 | N68: =Assumptions!N122 -> 0 | O68: =Assumptions!O122 -> 0 | P68: =Assumptions!P122 -> 0 | R68: =IF($R$5=1,_xlfn.FORMULATEXT(P68),"")
D69: =Historical!C73 -> Financing Cash Flow | E69: $'MM | I69: =SUM(I61:I68) -> -32.4 | J69: =SUM(J61:J68) -> 32 | K69: =SUM(K61:K68) -> 34.4 | L69: =SUM(L61:L68) -> -165.98679 | M69: =SUM(M61:M68) -> 129.13265 | N69: =SUM(N61:N68) -> 149.10554 | O69: =SUM(O61:O68) -> -254.33771 | P69: =SUM(P61:P68) -> -103.02536 | R69: =IF($R$5=1,_xlfn.FORMULATEXT(P69),"")
D71: =Historical!C75 -> Change in Cash Position | E71: $'MM | I71: =I69+I58+I52 -> -24.6 | J71: =J69+J58+J52 -> -1.5 | K71: =K69+K58+K52 -> -7.7 | L71: =L69+L58+L52 -> -199 | M71: =M69+M58+M52 -> 117.47996 | N71: =N69+N58+N52 -> 155.31083 | O71: =O69+O58+O52 -> -221.01332 | P71: =P69+P58+P52 -> -51.777471 | R71: =IF($R$5=1,_xlfn.FORMULATEXT(P71),"")
D72: =Historical!C76 -> Beginning Cash | E72: $'MM | I72: =Historical!G76 -> 232.8 | J72: =I73 -> 208.2 | K72: =J73 -> 206.7 | L72: =K73 -> 199 | M72: =L73 -> 0 | N72: =M73 -> 117.47996 | O72: =N73 -> 272.79079 | P72: =O73 -> 51.777471 | R72: =IF($R$5=1,_xlfn.FORMULATEXT(P72),"")
D73: =Historical!C77 -> Ending Cash | E73: $'MM | I73: =SUM(I71:I72) -> 208.2 | J73: =SUM(J71:J72) -> 206.7 | K73: =SUM(K71:K72) -> 199 | L73: =SUM(L71:L72) -> 0 | M73: =SUM(M71:M72) -> 117.47996 | N73: =SUM(N71:N72) -> 272.79079 | O73: =SUM(O71:O72) -> 51.777471 | P73: =SUM(P71:P72) -> 0 | R73: =IF($R$5=1,_xlfn.FORMULATEXT(P73),"")
C75: Balance Sheet
C77: =Historical!B86 -> ASSETS
D78: =Historical!C87 -> Cash and Equivalents | E78: $'MM | I78: =I73 -> 208.2 | J78: =J73 -> 206.7 | K78: =K73 -> 199 | L78: =L73 -> 0 | M78: =M73 -> 117.47996 | N78: =N73 -> 272.79079 | O78: =O73 -> 51.777471 | P78: =P73 -> 0 | R78: =IF($R$5=1,_xlfn.FORMULATEXT(P78),"")
D79: =Historical!C88 -> Accounts Receivable | E79: $'MM | I79: =Historical!G88 -> 16 | J79: =Historical!H88 -> 15.1 | K79: =Historical!I88 -> 20.2 | L79: =L269 -> 20.448387 | M79: =M269 -> 22.404182 | N79: =N269 -> 24.585367 | O79: =O269 -> 26.81214 | P79: =P269 -> 28.1278 | R79: =IF($R$5=1,_xlfn.FORMULATEXT(P79),"")
D80: =Historical!C89 -> Inventory | E80: $'MM | I80: =Historical!G89 -> 2.8 | J80: =Historical!H89 -> 3.6 | K80: =Historical!I89 -> 4.2 | L80: =L270 -> 4.3500907 | M80: =M270 -> 4.6654845 | N80: =N270 -> 5.0222181 | O80: =O270 -> 5.3825961 | P80: =P270 -> 5.616075 | R80: =IF($R$5=1,_xlfn.FORMULATEXT(P80),"")
D81: =Historical!C90 -> Other Current Assets | E81: $'MM | I81: =Historical!G90 -> 0.3 | J81: =Historical!H90 -> 0.2 | K81: =Historical!I90 -> 0.2 | L81: =L271 -> 0.30073951 | M81: =M271 -> 0.32254397 | N81: =N271 -> 0.34720642 | O81: =O271 -> 0.37212082 | P81: =P271 -> 0.38826217 | R81: =IF($R$5=1,_xlfn.FORMULATEXT(P81),"")
D82: =Historical!C91 -> Total Current Assets | E82: $'MM | I82: =SUM(I78:I81) -> 227.3 | J82: =SUM(J78:J81) -> 225.6 | K82: =SUM(K78:K81) -> 223.6 | L82: =SUM(L78:L81) -> 25.099217 | M82: =SUM(M78:M81) -> 144.87217 | N82: =SUM(N78:N81) -> 302.74558 | O82: =SUM(O78:O81) -> 84.344328 | P82: =SUM(P78:P81) -> 34.132138 | R82: =IF($R$5=1,_xlfn.FORMULATEXT(P82),"")
D84: =Historical!C93 -> Net PP&E | E84: $'MM | I84: =Historical!G93 -> 2332.1 | J84: =Historical!H93 -> 2445.6 | K84: =Historical!I93 -> 2542.2 | L84: =L247 -> 2624.356 | M84: =M247 -> 2694.2289 | N84: =N247 -> 2762.6283 | O84: =O247 -> 2820.2813 | P84: =P247 -> 2868.3407 | R84: =IF($R$5=1,_xlfn.FORMULATEXT(P84),"")
D85: =Historical!C94 -> Goodwill | E85: $'MM | I85: =Historical!G94 -> 46.6 | J85: =Historical!H94 -> 34.7 | K85: =Historical!I94 -> 31 | L85: =K85+Assumptions!L120 -> 31 | M85: =L85+Assumptions!M120 -> 31 | N85: =M85+Assumptions!N120 -> 31 | O85: =N85+Assumptions!O120 -> 31 | P85: =O85+Assumptions!P120 -> 31 | R85: =IF($R$5=1,_xlfn.FORMULATEXT(P85),"")
D86: =Historical!C95 -> Intangibles | E86: $'MM | I86: =Historical!G95 -> 15.5 | J86: =Historical!H95 -> 14.7 | K86: =Historical!I95 -> 13.1 | L86: =K86+Assumptions!L121 -> 13.1 | M86: =L86+Assumptions!M121 -> 13.1 | N86: =M86+Assumptions!N121 -> 13.1 | O86: =N86+Assumptions!O121 -> 13.1 | P86: =O86+Assumptions!P121 -> 13.1 | R86: =IF($R$5=1,_xlfn.FORMULATEXT(P86),"")
D87: =Historical!C96 -> Other Long term Assets | E87: $'MM | I87: =Historical!G96 -> 4.2 | J87: =Historical!H96 -> 3.5 | K87: =Historical!I96 -> 2.1 | L87: =K87+Assumptions!L122 -> 2.1 | M87: =L87+Assumptions!M122 -> 2.1 | N87: =M87+Assumptions!N122 -> 2.1 | O87: =N87+Assumptions!O122 -> 2.1 | P87: =O87+Assumptions!P122 -> 2.1 | R87: =IF($R$5=1,_xlfn.FORMULATEXT(P87),"")
D88: =Historical!C97 -> Total Long Term Assets | E88: $'MM | I88: =SUM(I84:I87) -> 2398.4 | J88: =SUM(J84:J87) -> 2498.5 | K88: =SUM(K84:K87) -> 2588.4 | L88: =SUM(L84:L87) -> 2670.556 | M88: =SUM(M84:M87) -> 2740.4289 | N88: =SUM(N84:N87) -> 2808.8283 | O88: =SUM(O84:O87) -> 2866.4813 | P88: =SUM(P84:P87) -> 2914.5407 | R88: =IF($R$5=1,_xlfn.FORMULATEXT(P88),"")
D90: =Historical!C99 -> Total Assets | E90: $'MM | I90: =I82+I88 -> 2625.7 | J90: =J82+J88 -> 2724.1 | K90: =K82+K88 -> 2812 | L90: =L82+L88 -> 2695.6552 | M90: =M82+M88 -> 2885.3011 | N90: =N82+N88 -> 3111.5739 | O90: =O82+O88 -> 2950.8257 | P90: =P82+P88 -> 2948.6729 | R90: =IF($R$5=1,_xlfn.FORMULATEXT(P90),"")
C93: =Historical!B102 -> LIABILITIES AND EQUITY
D94: =Historical!C103 -> Bank Debt - Revolver | E94: $'MM | I94: =Historical!G103 -> 0 | J94: =Historical!H103 -> 0 | K94: =Historical!I103 -> 0 | L94: =L374 -> 38.688904 | M94: =M374 -> 0 | N94: =N374 -> 0 | O94: =O374 -> 0 | P94: =P374 -> 75.330133 | R94: =IF($R$5=1,_xlfn.FORMULATEXT(P94),"")
D95: =Historical!C104 -> Accounts Payable | E95: $'MM | I95: =Historical!G104 -> 14.9 | J95: =Historical!H104 -> 21.5 | K95: =Historical!I104 -> 23.9 | L95: =L275 -> 24.642413 | M95: =M275 -> 26.429057 | N95: =N275 -> 28.449883 | O95: =O275 -> 30.491355 | P95: =P275 -> 31.813967 | R95: =IF($R$5=1,_xlfn.FORMULATEXT(P95),"")
D96: =Historical!C105 -> Other Current Liabilities | E96: $'MM | I96: =Historical!G105 -> 4.6 | J96: =Historical!H105 -> 5.1 | K96: =Historical!I105 -> 4.9 | L96: =L276 -> 6.0998478 | M96: =M276 -> 6.5421039 | N96: =N276 -> 7.0423281 | O96: =O276 -> 7.5476627 | P96: =P276 -> 7.8750549 | R96: =IF($R$5=1,_xlfn.FORMULATEXT(P96),"")
D97: =Historical!C106 -> Total Current Liabilities | E97: $'MM | I97: =SUM(I94:I96) -> 19.5 | J97: =SUM(J94:J96) -> 26.6 | K97: =SUM(K94:K96) -> 28.8 | L97: =SUM(L94:L96) -> 69.431165 | M97: =SUM(M94:M96) -> 32.971161 | N97: =SUM(N94:N96) -> 35.492211 | O97: =SUM(O94:O96) -> 38.039017 | P97: =SUM(P94:P96) -> 115.01915 | R97: =IF($R$5=1,_xlfn.FORMULATEXT(P97),"")
D99: =Historical!C108 -> Variable Rate Long Term Debt | E99: $'MM | I99: =Historical!G108 -> 577.7 | J99: =Historical!H108 -> 597.7 | K99: =Historical!I108 -> 622.7 | L99: =L344 -> 487.7 | M99: =M344 -> 352.7 | N99: =N344 -> 217.7 | O99: =O344 -> 82.7 | P99: =P344 -> 0 | R99: =IF($R$5=1,_xlfn.FORMULATEXT(P99),"")
D100: =Historical!C109 -> Fixed Rate Long Term Debt | E100: $'MM | I100: =Historical!G109 -> 174.6 | J100: =Historical!H109 -> 199.6 | K100: =Historical!I109 -> 224.6 | L100: =L334 -> 174.6 | M100: =M334 -> 124.6 | N100: =N334 -> 74.6 | O100: =O334 -> 24.6 | P100: =P334 -> 0 | R100: =IF($R$5=1,_xlfn.FORMULATEXT(P100),"")
D101: =Historical!C110 -> Deferred Income Taxes | E101: $'MM | I101: =Historical!G110 -> 10.4 | J101: =Historical!H110 -> 22.2 | K101: =Historical!I110 -> 30.6 | L101: =K101+L28 -> 32.225 | M101: =L101+M28 -> 33.85 | N101: =M101+N28 -> 35.475 | O101: =N101+O28 -> 37.1 | P101: =O101+P28 -> 38.725 | R101: =IF($R$5=1,_xlfn.FORMULATEXT(P101),"")
D102: =Historical!C111 -> Other Longterm Liabilities | E102: $'MM | I102: =Historical!G111 -> 2.4 | J102: =Historical!H111 -> 3.6 | K102: =Historical!I111 -> 3.2 | L102: =K102+Assumptions!L123 -> 3.2 | M102: =L102+Assumptions!M123 -> 3.2 | N102: =M102+Assumptions!N123 -> 3.2 | O102: =N102+Assumptions!O123 -> 3.2 | P102: =O102+Assumptions!P123 -> 3.2 | R102: =IF($R$5=1,_xlfn.FORMULATEXT(P102),"")
D103: =Historical!C112 -> Total Long Term Liabilities | E103: $'MM | I103: =SUM(I99:I102) -> 765.1 | J103: =SUM(J99:J102) -> 823.1 | K103: =SUM(K99:K102) -> 881.1 | L103: =SUM(L99:L102) -> 697.725 | M103: =SUM(M99:M102) -> 514.35 | N103: =SUM(N99:N102) -> 330.975 | O103: =SUM(O99:O102) -> 147.6 | P103: =SUM(P99:P102) -> 41.925 | R103: =IF($R$5=1,_xlfn.FORMULATEXT(P103),"")
D105: =Historical!C114 -> Total Liabilities | E105: $'MM | I105: =I97+I103 -> 784.6 | J105: =J97+J103 -> 849.7 | K105: =K97+K103 -> 909.9 | L105: =L97+L103 -> 767.15616 | M105: =M97+M103 -> 547.32116 | N105: =N97+N103 -> 366.46721 | O105: =O97+O103 -> 185.63902 | P105: =P97+P103 -> 156.94415 | R105: =IF($R$5=1,_xlfn.FORMULATEXT(P105),"")
D107: =Historical!C116 -> Preferred Shares | E107: $'MM | I107: =Historical!G116 -> 0 | J107: =Historical!H116 -> 0 | K107: =Historical!I116 -> 0 | L107: =L316 -> 0 | M107: =M316 -> 400 | N107: =N316 -> 800 | O107: =O316 -> 800 | P107: =P316 -> 800 | R107: =IF($R$5=1,_xlfn.FORMULATEXT(P107),"")
D108: =Historical!C117 -> Common Shares | E108: $'MM | I108: =Historical!G117 -> 1653.2 | J108: =Historical!H117 -> 1649.2 | K108: =Historical!I117 -> 1643.2 | L108: =L308 -> 1633.2 | M108: =M308 -> 1623.2 | N108: =N308 -> 1623.2 | O108: =O308 -> 1623.2 | P108: =P308 -> 1623.2 | R108: =IF($R$5=1,_xlfn.FORMULATEXT(P108),"")
D109: =Historical!C118 -> Retained Earnings | E109: $'MM | I109: =Historical!G118 -> 175.1 | J109: =Historical!H118 -> 211 | K109: =Historical!I118 -> 245 | L109: =L324 -> 281.39905 | M109: =M324 -> 300.87989 | N109: =N324 -> 308.00667 | O109: =O324 -> 328.08665 | P109: =P324 -> 354.62873 | R109: =IF($R$5=1,_xlfn.FORMULATEXT(P109),"")
D110: =Historical!C119 -> Other Shareholder equity | E110: $'MM | I110: =Historical!G119 -> 12.8 | J110: =Historical!H119 -> 14.2 | K110: =Historical!I119 -> 13.9 | L110: =K110+Assumptions!L124 -> 13.9 | M110: =L110+Assumptions!M124 -> 13.9 | N110: =M110+Assumptions!N124 -> 13.9 | O110: =N110+Assumptions!O124 -> 13.9 | P110: =O110+Assumptions!P124 -> 13.9 | R110: =IF($R$5=1,_xlfn.FORMULATEXT(P110),"")
D111: =Historical!C120 -> Shareholder's Equity | E111: $'MM | I111: =SUM(I107:I110) -> 1841.1 | J111: =SUM(J107:J110) -> 1874.4 | K111: =SUM(K107:K110) -> 1902.1 | L111: =SUM(L107:L110) -> 1928.4991 | M111: =SUM(M107:M110) -> 2337.9799 | N111: =SUM(N107:N110) -> 2745.1067 | O111: =SUM(O107:O110) -> 2765.1866 | P111: =SUM(P107:P110) -> 2791.7287 | R111: =IF($R$5=1,_xlfn.FORMULATEXT(P111),"")
C113: =Historical!B122 -> Total Liabilities and Equity | E113: $'MM | I113: =I111+I105 -> 2625.7 | J113: =J111+J105 -> 2724.1 | K113: =K111+K105 -> 2812 | L113: =L111+L105 -> 2695.6552 | M113: =M111+M105 -> 2885.3011 | N113: =N111+N105 -> 3111.5739 | O113: =O111+O105 -> 2950.8257 | P113: =P111+P105 -> 2948.6729 | R113: =IF($R$5=1,_xlfn.FORMULATEXT(P113),"")
D115: Balance Check | G115: =ROUND(SUM(I115:P115),2) -> 0 | I115: =ABS(I113-I90) -> 0 | J115: =ABS(J113-J90) -> 9.094947e-13 | K115: =ABS(K113-K90) -> 4.5474735e-13 | L115: =ABS(L113-L90) -> 4.5474735e-13 | M115: =ABS(M113-M90) -> 4.5474735e-13 | N115: =ABS(N113-N90) -> 4.5474735e-13 | O115: =ABS(O113-O90) -> 4.5474735e-13 | P115: =ABS(P113-P90) -> 9.094947e-13 | R115: =IF($R$5=1,_xlfn.FORMULATEXT(P115),"")
B117: Schedules and Calculations
C118: Revenue Schedule
C120: Capacity Limits
D121: =Assumptions!D23 -> Total Numbers of Properties | E121: =Assumptions!E23 -> unit | F121: =Assumptions!K23 -> 390
D122: =Assumptions!D24 -> Current Leasable Areas | E122: =Assumptions!E24 -> Square feet | F122: =Assumptions!K24 -> 1560000
D123: =Assumptions!D25 -> Land currently Built up | E123: =Assumptions!E25 -> % | F123: =Assumptions!K25 -> 0.6
D124: Total Land Stock | E124: Square feet | F124: =F122/F123 -> 2600000
D125: =Assumptions!D26 -> Land available for new property | E125: =Assumptions!E26 -> % | F125: =Assumptions!K26 -> 0.2
D126: Maximum Capacity for new Property | E126: Square feet | F126: =F124*F125 -> 520000
D127: Total Square feet per Property | E127: Square feet | F127: =F122/F121 -> 4000
D128: Maximum number of new property Units (Capacity) | E128: units | F128: =F126/F127 -> 130
D130: =Assumptions!D28 -> Additional Properties Assumption | E130: =Assumptions!E28 -> unit | L130: =Assumptions!L28 -> 30 | M130: =Assumptions!M28 -> 30 | N130: =Assumptions!N28 -> 30 | O130: =Assumptions!O28 -> 30 | P130: =Assumptions!P28 -> 30
C132: Property Stock Schedule
D133: Opening Balance | E133: units | L133: =K135 -> 130 | M133: =L135 -> 100 | N133: =M135 -> 70 | O133: =N135 -> 40 | P133: =O135 -> 10
...

Sheet Template
B2: =Cover!B4 -> Xcel Stores & Properties
C3: Sheet Name | I3: =IF(BalCheck=0,"Bal check: OK","ERROR") -> Bal check: OK | K3: {="Scenario: "&INDEX(S_List,S_Scenario)} -> Scenario: Base Case
I4: Actual | J4: Actual | K4: Actual | L4: Forecast | M4: Forecast | N4: Forecast | O4: Forecast | P4: Forecast
E5: units | F5: Inputs/drivers | I5: =Historical!G7 -> 2020 | J5: =I5+1 -> 2021 | K5: =J5+1 -> 2022 | L5: =K5+1 -> 2023 | M5: =L5+1 -> 2024 | N5: =M5+1 -> 2025 | O5: =N5+1 -> 2026 | P5: =O5+1 -> 2027
